tests/__init__.py
tests/tests.py
tests/app/__init__.py
tests/app/app.py
tests/app/config.py
tests/app/models.py
yAuth/__init__.py
yAuth-0.1.0.dist-info/LICENSE
yAuth-0.1.0.dist-info/METADATA
yAuth-0.1.0.dist-info/WHEEL
yAuth-0.1.0.dist-info/top_level.txt
yAuth-0.1.0.dist-info/RECORD
