Metadata-Version: 2.1
Name: yAuth
Version: 0.1.0
Summary: sanic-jwt extensions for yRest
Home-page: https://github.com/Garito/yAuth
Author: Garito
Author-email: garito@gmail.com
License: MIT
Keywords: auth yRest
Platform: UNKNOWN
Classifier: Development Status :: 4 - Beta
Classifier: Environment :: Plugins
Classifier: Intended Audience :: Developers
Classifier: License :: OSI Approved :: MIT License
Classifier: Programming Language :: Python :: 3
Classifier: Topic :: Security
Requires-Python: >=3.6
Requires-Dist: pyJWT
Requires-Dist: ySanic
Requires-Dist: yModel
